sonarkan/__init__.py
sonarkan/bspline.py
sonarkan/models.py
sonarkan/surrogate.py
sonarkan-1.0.7.dist-info/METADATA
sonarkan-1.0.7.dist-info/WHEEL
sonarkan-1.0.7.dist-info/top_level.txt
sonarkan-1.0.7.dist-info/RECORD
